pyTabela/__init__.py
pyTabela/pyTabela.py
PyTabela-0.0.1.3.dist-info/LICENSE
PyTabela-0.0.1.3.dist-info/METADATA
PyTabela-0.0.1.3.dist-info/WHEEL
PyTabela-0.0.1.3.dist-info/top_level.txt
PyTabela-0.0.1.3.dist-info/RECORD
