Metadata-Version: 2.1
Name: PyTabela
Version: 0.0.1.3
Summary: Pacote utilizado para criação de tabelas no python
Home-page: https://github.com/Pepyn0/PyTabela
Author: Pepyn0 & Vitoria Karolina Ferreira Sousa
Author-email: brpepy@gmail.com
License: UNKNOWN
Project-URL: Bug Tracker, https://github.com/Pepyn0/PyTabela
Platform: UNKNOWN
Classifier: Programming Language :: Python :: 3
Classifier: License :: OSI Approved :: MIT License
Classifier: Operating System :: OS Independent
Requires-Python: >=3.8
License-File: LICENSE
